nautobot_ddns/__init__.py
nautobot_ddns/admin.py
nautobot_ddns/background_tasks.py
nautobot_ddns/forms.py
nautobot_ddns/models.py
nautobot_ddns/signals.py
nautobot_ddns/tables.py
nautobot_ddns/template_content.py
nautobot_ddns/urls.py
nautobot_ddns/utils.py
nautobot_ddns/validators.py
nautobot_ddns/views.py
nautobot_ddns/templates/nautobot_ddns/ipaddress/dns_extra.html
nautobot_ddns/templates/nautobot_ddns/ipaddress/dns_info.html
nautobot_ddns/templates/nautobot_ddns/ipaddress/dns_refresh_button.html
nautobot_ddns-1.0.4.dist-info/LICENSE
nautobot_ddns-1.0.4.dist-info/METADATA
nautobot_ddns-1.0.4.dist-info/WHEEL
nautobot_ddns-1.0.4.dist-info/top_level.txt
nautobot_ddns-1.0.4.dist-info/RECORD
